unified_path/__init__.py
unified_path/path_helper.py
unified_path/unified_path.py
unified_path/unified_path_encoder.py
unified_path/validator.py
unified_path-1.0.dist-info/LICENSE
unified_path-1.0.dist-info/METADATA
unified_path-1.0.dist-info/WHEEL
unified_path-1.0.dist-info/top_level.txt
unified_path-1.0.dist-info/RECORD
