Metadata-Version: 2.1
Name: unified-path
Version: 1.0
Summary: A Python wrapper around pathlib providing an OS-independent path representation.
Home-page: https://github.com/emmcb/unified-path
Author: Emmanuel Chaboud
Classifier: License :: OSI Approved :: Apache Software License
Classifier: Programming Language :: Python :: 3
Classifier: Programming Language :: Python :: 3 :: Only
Classifier: Operating System :: OS Independent
Classifier: Topic :: Software Development :: Libraries :: Python Modules
Requires-Python: >=3
License-File: LICENSE
